[
  {
    "j": "色",
    "e": [
      "Colours"
    ]
  },
  {
    "j": "白",
    "e": [
      "white"
    ]
  },
  {
    "j": "黒",
    "e": [
      "black"
    ]
  },
  {
    "j": "赤",
    "e": [
      "red"
    ]
  },
  {
    "j": "紅",
    "e": [
      "crimson"
    ]
  },
  {
    "j": "青",
    "e": [
      "blue"
    ]
  },
  {
    "j": "黄",
    "e": [
      "yellow"
    ]
  },
  {
    "j": "緑",
    "e": [
      "green"
    ]
  },
  {
    "j": "金",
    "e": [
      "gold"
    ]
  },
  {
    "j": "銀",
    "e": [
      "silver"
    ]
  },
  {
    "j": "紫",
    "e": [
      "violet"
    ]
  },
  {
    "j": "紺",
    "e": [
      "dark blue"
    ]
  },
  {
    "j": "朱",
    "e": [
      "vermilion"
    ]
  },
  {
    "j": "褐",
    "e": [
      "brown"
    ]
  },
  {
    "j": "藍",
    "e": [
      "indigo"
    ]
  },
  {
    "j": "彩",
    "e": [
      "brightly coloured"
    ]
  },
  {
    "j": "形",
    "e": [
      "shape"
    ]
  },
  {
    "j": "体",
    "e": [
      "form"
    ]
  },
  {
    "j": "姿",
    "e": [
      "figure"
    ]
  },
  {
    "j": "模",
    "e": [
      "pattern"
    ]
  },
  {
    "j": "柄",
    "e": [
      "design, pattern"
    ]
  },
  {
    "j": "円",
    "e": [
      "circle"
    ]
  },
  {
    "j": "丸",
    "e": [
      "circular"
    ]
  },
  {
    "j": "曲",
    "e": [
      "curve"
    ]
  },
  {
    "j": "弧",
    "e": [
      "arc"
    ]
  },
  {
    "j": "環",
    "e": [
      "ring, surround"
    ]
  },
  {
    "j": "輪",
    "e": [
      "ring"
    ]
  },
  {
    "j": "凹",
    "e": [
      "concave"
    ]
  },
  {
    "j": "凸",
    "e": [
      "convex"
    ]
  },
  {
    "j": "角",
    "e": [
      "angle"
    ]
  },
  {
    "j": "斜",
    "e": [
      "diagonal"
    ]
  },
  {
    "j": "球",
    "e": [
      "sphere"
    ]
  },
  {
    "j": "圏",
    "e": [
      "sphere"
    ]
  },
  {
    "j": "玉",
    "e": [
      "ball"
    ]
  },
  {
    "j": "線",
    "e": [
      "line"
    ]
  },
  {
    "j": "列",
    "e": [
      "row, line"
    ]
  },
  {
    "j": "並",
    "e": [
      "line up"
    ]
  },
  {
    "j": "大",
    "e": [
      "large"
    ]
  },
  {
    "j": "巨",
    "e": [
      "huge"
    ]
  },
  {
    "j": "小",
    "e": [
      "small"
    ]
  },
  {
    "j": "微",
    "e": [
      "minute"
    ]
  },
  {
    "j": "狭",
    "e": [
      "narrow"
    ]
  },
  {
    "j": "端",
    "e": [
      "edge or border"
    ]
  },
  {
    "j": "縁",
    "e": [
      "edge"
    ]
  },
  {
    "j": "周",
    "e": [
      "perimeter"
    ]
  },
  {
    "j": "境",
    "e": [
      "boundary"
    ]
  },
  {
    "j": "枠",
    "e": [
      "frame, border"
    ]
  },
  {
    "j": "端",
    "e": [
      "end, tip"
    ]
  },
  {
    "j": "側",
    "e": [
      "side"
    ]
  },
  {
    "j": "隅",
    "e": [
      "corner"
    ]
  },
  {
    "j": "高",
    "e": [
      "tall"
    ]
  },
  {
    "j": "長",
    "e": [
      "long"
    ]
  },
  {
    "j": "短",
    "e": [
      "short"
    ]
  },
  {
    "j": "広",
    "e": [
      "wide"
    ]
  },
  {
    "j": "幅",
    "e": [
      "width"
    ]
  },
  {
    "j": "硬",
    "e": [
      "hard"
    ]
  },
  {
    "j": "軟",
    "e": [
      "soft"
    ]
  },
  {
    "j": "重",
    "e": [
      "heavy"
    ]
  },
  {
    "j": "軽",
    "e": [
      "light (weight)"
    ]
  },
  {
    "j": "固",
    "e": [
      "solid, firm"
    ]
  },
  {
    "j": "液",
    "e": [
      "liquid"
    ]
  },
  {
    "j": "強",
    "e": [
      "strong"
    ]
  },
  {
    "j": "弱",
    "e": [
      "weak"
    ]
  },
  {
    "j": "厚",
    "e": [
      "thick"
    ]
  },
  {
    "j": "濃",
    "e": [
      "thick, concentrated"
    ]
  },
  {
    "j": "薄",
    "e": [
      "dilute, thin"
    ]
  },
  {
    "j": "細",
    "e": [
      "slender"
    ]
  },
  {
    "j": "緻",
    "e": [
      "fine, delicate"
    ]
  },
  {
    "j": "微",
    "e": [
      "delicate"
    ]
  },
  {
    "j": "鋭",
    "e": [
      "sharp"
    ]
  },
  {
    "j": "太",
    "e": [
      "fat, thick"
    ]
  },
  {
    "j": "深",
    "e": [
      "deep"
    ]
  },
  {
    "j": "浅",
    "e": [
      "shallow"
    ]
  },
  {
    "j": "暑",
    "e": [
      "hot"
    ]
  },
  {
    "j": "熱",
    "e": [
      "hot"
    ]
  },
  {
    "j": "温",
    "e": [
      "warm"
    ]
  },
  {
    "j": "暖",
    "e": [
      "warm"
    ]
  },
  {
    "j": "冷",
    "e": [
      "cold"
    ]
  },
  {
    "j": "寒",
    "e": [
      "cold"
    ]
  },
  {
    "j": "干",
    "e": [
      "dry"
    ]
  },
  {
    "j": "乾",
    "e": [
      "dry"
    ]
  },
  {
    "j": "湿",
    "e": [
      "damp"
    ]
  },
  {
    "j": "潤",
    "e": [
      "moist"
    ]
  },
  {
    "j": "浄",
    "e": [
      "clean"
    ]
  },
  {
    "j": "汚",
    "e": [
      "dirty"
    ]
  },
  {
    "j": "粘",
    "e": [
      "sticky"
    ]
  },
  {
    "j": "艶",
    "e": [
      "glossy"
    ]
  },
  {
    "j": "北",
    "e": [
      "north"
    ]
  },
  {
    "j": "南",
    "e": [
      "south"
    ]
  },
  {
    "j": "東",
    "e": [
      "east"
    ]
  },
  {
    "j": "西",
    "e": [
      "west"
    ]
  },
  {
    "j": "左",
    "e": [
      "left"
    ]
  },
  {
    "j": "右",
    "e": [
      "right"
    ]
  },
  {
    "j": "下",
    "e": [
      "down"
    ]
  },
  {
    "j": "上",
    "e": [
      "up"
    ]
  },
  {
    "j": "前",
    "e": [
      "front"
    ]
  },
  {
    "j": "後",
    "e": [
      "back"
    ]
  },
  {
    "j": "裏",
    "e": [
      "rear, back"
    ]
  },
  {
    "j": "底",
    "e": [
      "bottom"
    ]
  },
  {
    "j": "外",
    "e": [
      "outside"
    ]
  },
  {
    "j": "中",
    "e": [
      "inside/middle"
    ]
  },
  {
    "j": "内",
    "e": [
      "inside"
    ]
  },
  {
    "j": "央",
    "e": [
      "centre"
    ]
  },
  {
    "j": "奥",
    "e": [
      "interior"
    ]
  },
  {
    "j": "間",
    "e": [
      "between"
    ]
  },
  {
    "j": "入",
    "e": [
      "direction in"
    ]
  },
  {
    "j": "出",
    "e": [
      "direction out"
    ]
  },
  {
    "j": "方",
    "e": [
      "direction"
    ]
  },
  {
    "j": "近",
    "e": [
      "near"
    ]
  },
  {
    "j": "遠",
    "e": [
      "distant"
    ]
  },
  {
    "j": "向",
    "e": [
      "toward"
    ]
  },
  {
    "j": "来",
    "e": [
      "come"
    ]
  },
  {
    "j": "行",
    "e": [
      "go"
    ]
  },
  {
    "j": "旅",
    "e": [
      "travel"
    ]
  },
  {
    "j": "往",
    "e": [
      "go, depart"
    ]
  },
  {
    "j": "帰",
    "e": [
      "return"
    ]
  },
  {
    "j": "参",
    "e": [
      "go (esp. visit)"
    ]
  },
  {
    "j": "落",
    "e": [
      "fall, drop"
    ]
  },
  {
    "j": "赴",
    "e": [
      "go to"
    ]
  },
  {
    "j": "越",
    "e": [
      "go beyond, exceed"
    ]
  },
  {
    "j": "倒",
    "e": [
      "fall over"
    ]
  },
  {
    "j": "墜",
    "e": [
      "fall down, crash"
    ]
  },
  {
    "j": "揚",
    "e": [
      "raise, elevate"
    ]
  },
  {
    "j": "数",
    "e": [
      "number"
    ]
  },
  {
    "j": "零",
    "e": [
      "zero"
    ]
  },
  {
    "j": "一",
    "e": [
      "one"
    ]
  },
  {
    "j": "二",
    "e": [
      "two"
    ]
  },
  {
    "j": "三",
    "e": [
      "three"
    ]
  },
  {
    "j": "四",
    "e": [
      "four"
    ]
  },
  {
    "j": "五",
    "e": [
      "five"
    ]
  },
  {
    "j": "六",
    "e": [
      "six"
    ]
  },
  {
    "j": "七",
    "e": [
      "seven"
    ]
  },
  {
    "j": "八",
    "e": [
      "eight"
    ]
  },
  {
    "j": "九",
    "e": [
      "nine"
    ]
  },
  {
    "j": "十",
    "e": [
      "ten"
    ]
  },
  {
    "j": "百",
    "e": [
      "100"
    ]
  },
  {
    "j": "千",
    "e": [
      "1,000"
    ]
  },
  {
    "j": "万",
    "e": [
      "10,000"
    ]
  },
  {
    "j": "億",
    "e": [
      "100,000,000"
    ]
  },
  {
    "j": "兆",
    "e": [
      "1,000,000,000,000"
    ]
  },
  {
    "j": "第",
    "e": [
      "ordinal marker"
    ]
  },
  {
    "j": "初",
    "e": [
      "first"
    ]
  },
  {
    "j": "乙",
    "e": [
      "second (ordinal)"
    ]
  },
  {
    "j": "丙",
    "e": [
      "third (ordinal)"
    ]
  },
  {
    "j": "桁",
    "e": [
      "digit"
    ]
  },
  {
    "j": "双",
    "e": [
      "pair"
    ]
  },
  {
    "j": "多",
    "e": [
      "many"
    ]
  },
  {
    "j": "少",
    "e": [
      "few"
    ]
  },
  {
    "j": "半",
    "e": [
      "half"
    ]
  },
  {
    "j": "両",
    "e": [
      "both"
    ]
  },
  {
    "j": "各",
    "e": [
      "each"
    ]
  },
  {
    "j": "毎",
    "e": [
      "every"
    ]
  },
  {
    "j": "次",
    "e": [
      "next"
    ]
  },
  {
    "j": "翌",
    "e": [
      "the following"
    ]
  },
  {
    "j": "番",
    "e": [
      "numerical order"
    ]
  },
  {
    "j": "順",
    "e": [
      "sequence"
    ]
  },
  {
    "j": "序",
    "e": [
      "sequence"
    ]
  },
  {
    "j": "個",
    "e": [
      "general counter"
    ]
  },
  {
    "j": "台",
    "e": [
      "counter for machines and vehicles"
    ]
  },
  {
    "j": "枚",
    "e": [
      "counter for flat things"
    ]
  },
  {
    "j": "本",
    "e": [
      "counter for cylindrical things"
    ]
  },
  {
    "j": "隻",
    "e": [
      "counter for ships"
    ]
  },
  {
    "j": "冊",
    "e": [
      "counter for books"
    ]
  },
  {
    "j": "匹",
    "e": [
      "counter for animals"
    ]
  },
  {
    "j": "疋",
    "e": [
      "counter for small animals or insects"
    ]
  },
  {
    "j": "頭",
    "e": [
      "counter for large animals"
    ]
  },
  {
    "j": "羽",
    "e": [
      "counter for birds and rabbits"
    ]
  },
  {
    "j": "箇",
    "e": [
      "counter for articles"
    ]
  },
  {
    "j": "足",
    "e": [
      "counter for pairs of footwear"
    ]
  },
  {
    "j": "札",
    "e": [
      "counter for bonds, tickets"
    ]
  },
  {
    "j": "杯",
    "e": [
      "counter for cupfuls"
    ]
  },
  {
    "j": "軒",
    "e": [
      "counter for houses"
    ]
  },
  {
    "j": "戸",
    "e": [
      "counter for houses"
    ]
  },
  {
    "j": "輪",
    "e": [
      "counter for wheels and flowers"
    ]
  },
  {
    "j": "畳",
    "e": [
      "counter for tatami mats"
    ]
  },
  {
    "j": "斤",
    "e": [
      "counter for loaves of bread"
    ]
  },
  {
    "j": "丁",
    "e": [
      "miscellaneous counter"
    ]
  },
  {
    "j": "算",
    "e": [
      "calculation"
    ]
  },
  {
    "j": "倍",
    "e": [
      "times, double"
    ]
  },
  {
    "j": "増",
    "e": [
      "increase, add"
    ]
  },
  {
    "j": "殖",
    "e": [
      "increase"
    ]
  },
  {
    "j": "耗",
    "e": [
      "decrease, consume"
    ]
  },
  {
    "j": "減",
    "e": [
      "dwindle, decrease"
    ]
  },
  {
    "j": "縮",
    "e": [
      "shrink, contract"
    ]
  },
  {
    "j": "加",
    "e": [
      "add to"
    ]
  },
  {
    "j": "除",
    "e": [
      "division"
    ]
  },
  {
    "j": "分",
    "e": [
      "divide"
    ]
  },
  {
    "j": "剖",
    "e": [
      "split in two"
    ]
  },
  {
    "j": "尺",
    "e": [
      "Japanese foot (around 30 cm)"
    ]
  },
  {
    "j": "寸",
    "e": [
      "1/10 Japanese foot (around 3 cm)"
    ]
  },
  {
    "j": "厘",
    "e": [
      "(around 0.3 mm)"
    ]
  },
  {
    "j": "里",
    "e": [
      "league (around 3.9 km)"
    ]
  },
  {
    "j": "坪",
    "e": [
      "two-mat area (around 3.3 m²)"
    ]
  },
  {
    "j": "畝",
    "e": [
      "30 tsubo (around 100 m²)"
    ]
  },
  {
    "j": "勺",
    "e": [
      "ladle (around 18 ml)"
    ]
  },
  {
    "j": "升",
    "e": [
      "(around 1.8 l)"
    ]
  },
  {
    "j": "斗",
    "e": [
      "(around 18 l)"
    ]
  },
  {
    "j": "石",
    "e": [
      "(around 180 l)"
    ]
  },
  {
    "j": "匁",
    "e": [
      "(around 3.75 grams)"
    ]
  },
  {
    "j": "斤",
    "e": [
      "(around 600 g)"
    ]
  },
  {
    "j": "日",
    "e": [
      "day"
    ]
  },
  {
    "j": "週",
    "e": [
      "week"
    ]
  },
  {
    "j": "月",
    "e": [
      "month"
    ]
  },
  {
    "j": "年",
    "e": [
      "year"
    ]
  },
  {
    "j": "曜",
    "e": [
      "day of week"
    ]
  },
  {
    "j": "暦",
    "e": [
      "calendar"
    ]
  },
  {
    "j": "朝",
    "e": [
      "morning"
    ]
  },
  {
    "j": "午",
    "e": [
      "noon"
    ]
  },
  {
    "j": "昼",
    "e": [
      "daytime"
    ]
  },
  {
    "j": "夕",
    "e": [
      "evening"
    ]
  },
  {
    "j": "晩",
    "e": [
      "evening"
    ]
  },
  {
    "j": "宵",
    "e": [
      "early evening"
    ]
  },
  {
    "j": "夜",
    "e": [
      "night"
    ]
  },
  {
    "j": "暁",
    "e": [
      "sunrise"
    ]
  },
  {
    "j": "旭",
    "e": [
      "rising sun"
    ]
  },
  {
    "j": "旦",
    "e": [
      "sunrise"
    ]
  },
  {
    "j": "暮",
    "e": [
      "sunset"
    ]
  },
  {
    "j": "時",
    "e": [
      "time, hour"
    ]
  },
  {
    "j": "分",
    "e": [
      "minute"
    ]
  },
  {
    "j": "秒",
    "e": [
      "second"
    ]
  },
  {
    "j": "今",
    "e": [
      "now"
    ]
  },
  {
    "j": "早",
    "e": [
      "early"
    ]
  },
  {
    "j": "遅",
    "e": [
      "late"
    ]
  },
  {
    "j": "前",
    "e": [
      "before"
    ]
  },
  {
    "j": "後",
    "e": [
      "after"
    ]
  },
  {
    "j": "久",
    "e": [
      "long ago"
    ]
  },
  {
    "j": "旧",
    "e": [
      "former"
    ]
  },
  {
    "j": "曽",
    "e": [
      "formerly"
    ]
  },
  {
    "j": "近",
    "e": [
      "recent"
    ]
  },
  {
    "j": "先",
    "e": [
      "ahead, previous"
    ]
  },
  {
    "j": "間",
    "e": [
      "interval of time"
    ]
  },
  {
    "j": "期",
    "e": [
      "time period"
    ]
  },
  {
    "j": "暫",
    "e": [
      "a while"
    ]
  },
  {
    "j": "紀",
    "e": [
      "era"
    ]
  },
  {
    "j": "昨",
    "e": [
      "previous time"
    ]
  },
  {
    "j": "回",
    "e": [
      "number of times"
    ]
  },
  {
    "j": "頃",
    "e": [
      "time, about"
    ]
  },
  {
    "j": "際",
    "e": [
      "moment, occasion"
    ]
  },
  {
    "j": "度",
    "e": [
      "number of times"
    ]
  },
  {
    "j": "昔",
    "e": [
      "antiquity"
    ]
  },
  {
    "j": "永",
    "e": [
      "eternity"
    ]
  },
  {
    "j": "旬",
    "e": [
      "period of 10 days"
    ]
  },
  {
    "j": "始",
    "e": [
      "begin"
    ]
  },
  {
    "j": "終",
    "e": [
      "end"
    ]
  },
  {
    "j": "古",
    "e": [
      "old"
    ]
  },
  {
    "j": "老",
    "e": [
      "old"
    ]
  },
  {
    "j": "若",
    "e": [
      "young"
    ]
  },
  {
    "j": "新",
    "e": [
      "new"
    ]
  },
  {
    "j": "季",
    "e": [
      "season"
    ]
  },
  {
    "j": "候",
    "e": [
      "season"
    ]
  },
  {
    "j": "節",
    "e": [
      "season, period"
    ]
  },
  {
    "j": "春",
    "e": [
      "spring"
    ]
  },
  {
    "j": "夏",
    "e": [
      "summer"
    ]
  },
  {
    "j": "秋",
    "e": [
      "autumn"
    ]
  },
  {
    "j": "冬",
    "e": [
      "winter"
    ]
  },
  {
    "j": "曜",
    "e": [
      "weekday"
    ]
  },
  {
    "j": "日",
    "e": [
      "Sunday"
    ]
  },
  {
    "j": "月",
    "e": [
      "Monday"
    ]
  },
  {
    "j": "火",
    "e": [
      "Tuesday"
    ]
  },
  {
    "j": "水",
    "e": [
      "Wednesday"
    ]
  },
  {
    "j": "木",
    "e": [
      "Thursday"
    ]
  },
  {
    "j": "金",
    "e": [
      "Friday"
    ]
  },
  {
    "j": "土",
    "e": [
      "Saturday"
    ]
  },
  {
    "j": "日",
    "e": [
      "sun"
    ]
  },
  {
    "j": "陽yang principle",
    "e": [
      "陽 sun or yang principle"
    ]
  },
  {
    "j": "月",
    "e": [
      "moon"
    ]
  },
  {
    "j": "星",
    "e": [
      "star"
    ]
  },
  {
    "j": "天",
    "e": [
      "sky or heaven"
    ]
  },
  {
    "j": "空",
    "e": [
      "sky or void"
    ]
  },
  {
    "j": "気",
    "e": [
      "air"
    ]
  },
  {
    "j": "宇",
    "e": [
      "universe"
    ]
  },
  {
    "j": "金",
    "e": [
      "metal or gold"
    ]
  },
  {
    "j": "銀",
    "e": [
      "silver"
    ]
  },
  {
    "j": "銅",
    "e": [
      "copper"
    ]
  },
  {
    "j": "鉛",
    "e": [
      "lead"
    ]
  },
  {
    "j": "鉄",
    "e": [
      "iron"
    ]
  },
  {
    "j": "銑",
    "e": [
      "pig iron"
    ]
  },
  {
    "j": "鋼",
    "e": [
      "steel"
    ]
  },
  {
    "j": "鉱",
    "e": [
      "ore"
    ]
  },
  {
    "j": "晶",
    "e": [
      "crystal"
    ]
  },
  {
    "j": "玉",
    "e": [
      "jewel"
    ]
  },
  {
    "j": "珠",
    "e": [
      "pearl or jewel"
    ]
  },
  {
    "j": "水",
    "e": [
      "water"
    ]
  },
  {
    "j": "氷",
    "e": [
      "ice"
    ]
  },
  {
    "j": "汽",
    "e": [
      "steam, vapour"
    ]
  },
  {
    "j": "石",
    "e": [
      "stone"
    ]
  },
  {
    "j": "炭",
    "e": [
      "coal"
    ]
  },
  {
    "j": "灰",
    "e": [
      "ash"
    ]
  },
  {
    "j": "土",
    "e": [
      "earth"
    ]
  },
  {
    "j": "地",
    "e": [
      "ground or earth"
    ]
  },
  {
    "j": "砂",
    "e": [
      "sand"
    ]
  },
  {
    "j": "沙",
    "e": [
      "sand"
    ]
  },
  {
    "j": "泥",
    "e": [
      "mud"
    ]
  },
  {
    "j": "塩",
    "e": [
      "salt"
    ]
  },
  {
    "j": "丹",
    "e": [
      "cinnabar"
    ]
  },
  {
    "j": "硫",
    "e": [
      "sulphur"
    ]
  },
  {
    "j": "酸",
    "e": [
      "acid, oxygen"
    ]
  },
  {
    "j": "窒",
    "e": [
      "nitrogen"
    ]
  },
  {
    "j": "材",
    "e": [
      "timber, material"
    ]
  },
  {
    "j": "油",
    "e": [
      "oil"
    ]
  },
  {
    "j": "脂",
    "e": [
      "fat"
    ]
  },
  {
    "j": "雲",
    "e": [
      "cloud"
    ]
  },
  {
    "j": "曇",
    "e": [
      "cloud"
    ]
  },
  {
    "j": "雨",
    "e": [
      "rain"
    ]
  },
  {
    "j": "虹",
    "e": [
      "rainbow"
    ]
  },
  {
    "j": "風",
    "e": [
      "wind"
    ]
  },
  {
    "j": "雪",
    "e": [
      "snow"
    ]
  },
  {
    "j": "嵐",
    "e": [
      "storm"
    ]
  },
  {
    "j": "候",
    "e": [
      "climate"
    ]
  },
  {
    "j": "晴",
    "e": [
      "fine weather"
    ]
  },
  {
    "j": "霞",
    "e": [
      "haze or mist"
    ]
  },
  {
    "j": "雷",
    "e": [
      "lightning or thunder"
    ]
  },
  {
    "j": "霧",
    "e": [
      "fog or mist"
    ]
  },
  {
    "j": "霜",
    "e": [
      "frost"
    ]
  },
  {
    "j": "露",
    "e": [
      "dew"
    ]
  },
  {
    "j": "波",
    "e": [
      "wave"
    ]
  },
  {
    "j": "潮",
    "e": [
      "tide"
    ]
  },
  {
    "j": "渦",
    "e": [
      "whirlpool"
    ]
  },
  {
    "j": "洪",
    "e": [
      "flood"
    ]
  },
  {
    "j": "震",
    "e": [
      "earthquake"
    ]
  },
  {
    "j": "災",
    "e": [
      "natural disaster"
    ]
  },
  {
    "j": "暗",
    "e": [
      "dark"
    ]
  },
  {
    "j": "闇",
    "e": [
      "dark"
    ]
  },
  {
    "j": "冥",
    "e": [
      "dark"
    ]
  },
  {
    "j": "光",
    "e": [
      "light"
    ]
  },
  {
    "j": "明",
    "e": [
      "light"
    ]
  },
  {
    "j": "陰yin principle",
    "e": [
      "陰 yin principle or shadow"
    ]
  },
  {
    "j": "影",
    "e": [
      "shadow"
    ]
  },
  {
    "j": "煙",
    "e": [
      "smoke or fumes"
    ]
  },
  {
    "j": "電",
    "e": [
      "electricity"
    ]
  },
  {
    "j": "磁",
    "e": [
      "magnet"
    ]
  },
  {
    "j": "火",
    "e": [
      "fire"
    ]
  },
  {
    "j": "炎",
    "e": [
      "blaze"
    ]
  },
  {
    "j": "陸",
    "e": [
      "land"
    ]
  },
  {
    "j": "野",
    "e": [
      "field"
    ]
  },
  {
    "j": "畑",
    "e": [
      "field"
    ]
  },
  {
    "j": "原",
    "e": [
      "field"
    ]
  },
  {
    "j": "田",
    "e": [
      "rice paddy"
    ]
  },
  {
    "j": "牧",
    "e": [
      "pasture"
    ]
  },
  {
    "j": "里",
    "e": [
      "countryside"
    ]
  },
  {
    "j": "壌",
    "e": [
      "fertile soil"
    ]
  },
  {
    "j": "漠",
    "e": [
      "desert"
    ]
  },
  {
    "j": "山",
    "e": [
      "mountain"
    ]
  },
  {
    "j": "岳",
    "e": [
      "peak or mountain"
    ]
  },
  {
    "j": "峰",
    "e": [
      "peak"
    ]
  },
  {
    "j": "峠",
    "e": [
      "mountain pass"
    ]
  },
  {
    "j": "丘",
    "e": [
      "hill"
    ]
  },
  {
    "j": "岡",
    "e": [
      "hill"
    ]
  },
  {
    "j": "阜",
    "e": [
      "hill"
    ]
  },
  {
    "j": "坂",
    "e": [
      "slope"
    ]
  },
  {
    "j": "麓",
    "e": [
      "foot of mountain"
    ]
  },
  {
    "j": "堤",
    "e": [
      "embankment"
    ]
  },
  {
    "j": "谷",
    "e": [
      "valley"
    ]
  },
  {
    "j": "溪",
    "e": [
      "mountain stream or valley"
    ]
  },
  {
    "j": "峡",
    "e": [
      "gorge"
    ]
  },
  {
    "j": "渓",
    "e": [
      "ravine"
    ]
  },
  {
    "j": "窟",
    "e": [
      "cave"
    ]
  },
  {
    "j": "岩",
    "e": [
      "rock or boulder"
    ]
  },
  {
    "j": "巌",
    "e": [
      "rock or boulder"
    ]
  },
  {
    "j": "漠",
    "e": [
      "desert"
    ]
  },
  {
    "j": "川",
    "e": [
      "river"
    ]
  },
  {
    "j": "河",
    "e": [
      "river or stream"
    ]
  },
  {
    "j": "泉",
    "e": [
      "water spring"
    ]
  },
  {
    "j": "滝",
    "e": [
      "waterfall"
    ]
  },
  {
    "j": "瀬",
    "e": [
      "shallows, rapids"
    ]
  },
  {
    "j": "堀",
    "e": [
      "ditch"
    ]
  },
  {
    "j": "畔",
    "e": [
      "levee"
    ]
  },
  {
    "j": "沢",
    "e": [
      "swamp"
    ]
  },
  {
    "j": "沼",
    "e": [
      "marsh"
    ]
  },
  {
    "j": "海",
    "e": [
      "ocean or sea"
    ]
  },
  {
    "j": "洋",
    "e": [
      "ocean"
    ]
  },
  {
    "j": "沖",
    "e": [
      "open sea"
    ]
  },
  {
    "j": "湖",
    "e": [
      "lake"
    ]
  },
  {
    "j": "池",
    "e": [
      "pond"
    ]
  },
  {
    "j": "潟",
    "e": [
      "lagoon"
    ]
  },
  {
    "j": "礁",
    "e": [
      "reef"
    ]
  },
  {
    "j": "江",
    "e": [
      "creek or bay"
    ]
  },
  {
    "j": "湾",
    "e": [
      "bay, gulf"
    ]
  },
  {
    "j": "岸",
    "e": [
      "shore"
    ]
  },
  {
    "j": "磯",
    "e": [
      "seashore"
    ]
  },
  {
    "j": "浜",
    "e": [
      "beach"
    ]
  },
  {
    "j": "浦",
    "e": [
      "bay, beach"
    ]
  },
  {
    "j": "崖",
    "e": [
      "cliff"
    ]
  },
  {
    "j": "崎",
    "e": [
      "promontory or cape"
    ]
  },
  {
    "j": "埼",
    "e": [
      "promontory"
    ]
  },
  {
    "j": "岬",
    "e": [
      "headland"
    ]
  },
  {
    "j": "島",
    "e": [
      "island"
    ]
  },
  {
    "j": "犬",
    "e": [
      "dog"
    ]
  },
  {
    "j": "狗",
    "e": [
      "dog"
    ]
  },
  {
    "j": "猫",
    "e": [
      "cat"
    ]
  },
  {
    "j": "鼠",
    "e": [
      "mouse"
    ]
  },
  {
    "j": "兎",
    "e": [
      "rabbit"
    ]
  },
  {
    "j": "馬",
    "e": [
      "horse"
    ]
  },
  {
    "j": "牛",
    "e": [
      "cow"
    ]
  },
  {
    "j": "羊",
    "e": [
      "sheep"
    ]
  },
  {
    "j": "豚",
    "e": [
      "pig"
    ]
  },
  {
    "j": "鹿",
    "e": [
      "deer"
    ]
  },
  {
    "j": "獣",
    "e": [
      "beast"
    ]
  },
  {
    "j": "畜",
    "e": [
      "livestock"
    ]
  },
  {
    "j": "象",
    "e": [
      "elephant"
    ]
  },
  {
    "j": "虎",
    "e": [
      "tiger"
    ]
  },
  {
    "j": "熊",
    "e": [
      "bear"
    ]
  },
  {
    "j": "狼",
    "e": [
      "wolf"
    ]
  },
  {
    "j": "狐",
    "e": [
      "fox"
    ]
  },
  {
    "j": "狸tanuki",
    "e": [
      "狸 raccoon dog (tanuki)"
    ]
  },
  {
    "j": "猿",
    "e": [
      "monkey"
    ]
  },
  {
    "j": "龜亀",
    "e": [
      "龜/亀 turtle"
    ]
  },
  {
    "j": "鯆",
    "e": [
      "dolphin"
    ]
  },
  {
    "j": "鯨",
    "e": [
      "whale"
    ]
  },
  {
    "j": "虫",
    "e": [
      "insect"
    ]
  },
  {
    "j": "昆",
    "e": [
      "insect"
    ]
  },
  {
    "j": "蜂",
    "e": [
      "bee"
    ]
  },
  {
    "j": "蚊",
    "e": [
      "mosquito"
    ]
  },
  {
    "j": "蚕",
    "e": [
      "silkworm"
    ]
  },
  {
    "j": "蛍",
    "e": [
      "firefly"
    ]
  },
  {
    "j": "蛇",
    "e": [
      "snake"
    ]
  },
  {
    "j": "鰐",
    "e": [
      "alligator or crocodile"
    ]
  },
  {
    "j": "魚",
    "e": [
      "fish"
    ]
  },
  {
    "j": "貝",
    "e": [
      "shellfish"
    ]
  },
  {
    "j": "鯉carp",
    "e": [
      "鯉 carp"
    ]
  },
  {
    "j": "鮒crucian carp",
    "e": [
      "鮒 crucian carp"
    ]
  },
  {
    "j": "鮠minnow",
    "e": [
      "鮠 minnow"
    ]
  },
  {
    "j": "鱒trout",
    "e": [
      "鱒 trout"
    ]
  },
  {
    "j": "鮭salmon",
    "e": [
      "鮭 salmon"
    ]
  },
  {
    "j": "鱸sea bass",
    "e": [
      "鱸 sea bass"
    ]
  },
  {
    "j": "鯛sea bream",
    "e": [
      "鯛 sea bream"
    ]
  },
  {
    "j": "鰌stone loach",
    "e": [
      "鰌 stone loach"
    ]
  },
  {
    "j": "鱈cod",
    "e": [
      "鱈 cod"
    ]
  },
  {
    "j": "鰻eel",
    "e": [
      "鰻 eel"
    ]
  },
  {
    "j": "鯊goby",
    "e": [
      "鯊 goby"
    ]
  },
  {
    "j": "鯖mackerel",
    "e": [
      "鯖 mackerel"
    ]
  },
  {
    "j": "鰯sardine",
    "e": [
      "鰯 sardine"
    ]
  },
  {
    "j": "鯵scadhorse mackerel",
    "e": [
      "鯵 scad / horse mackerel"
    ]
  },
  {
    "j": "鰊herring",
    "e": [
      "鰊 herring"
    ]
  },
  {
    "j": "鰍bullhead",
    "e": [
      "鰍 bullhead"
    ]
  },
  {
    "j": "鯰catfish",
    "e": [
      "鯰 catfish"
    ]
  },
  {
    "j": "鰈鮃flounder",
    "e": [
      "鰈/鮃 flounder"
    ]
  },
  {
    "j": "鰤amberjack",
    "e": [
      "鰤 amberjack"
    ]
  },
  {
    "j": "鮃sole",
    "e": [
      "鮃 sole"
    ]
  },
  {
    "j": "鮫shark",
    "e": [
      "鮫 shark"
    ]
  },
  {
    "j": "鳥",
    "e": [
      "bird"
    ]
  },
  {
    "j": "鶏",
    "e": [
      "chicken"
    ]
  },
  {
    "j": "鴨",
    "e": [
      "duck"
    ]
  },
  {
    "j": "鷹",
    "e": [
      "hawk"
    ]
  },
  {
    "j": "鶴",
    "e": [
      "crane"
    ]
  },
  {
    "j": "雀",
    "e": [
      "sparrow"
    ]
  },
  {
    "j": "梟owl",
    "e": [
      "梟 owl"
    ]
  },
  {
    "j": "燕swallow",
    "e": [
      "燕 swallow"
    ]
  },
  {
    "j": "烏鴉crow",
    "e": [
      "烏/鴉 crow"
    ]
  },
  {
    "j": "羽",
    "e": [
      "feather, wing"
    ]
  },
  {
    "j": "翼",
    "e": [
      "wing"
    ]
  },
  {
    "j": "毛",
    "e": [
      "fur"
    ]
  },
  {
    "j": "尾",
    "e": [
      "tail"
    ]
  },
  {
    "j": "牙",
    "e": [
      "tusk, fang"
    ]
  },
  {
    "j": "角",
    "e": [
      "horn"
    ]
  },
  {
    "j": "爪",
    "e": [
      "claw"
    ]
  },
  {
    "j": "植",
    "e": [
      "plant"
    ]
  },
  {
    "j": "木",
    "e": [
      "tree"
    ]
  },
  {
    "j": "樹",
    "e": [
      "tree"
    ]
  },
  {
    "j": "林",
    "e": [
      "grove"
    ]
  },
  {
    "j": "森",
    "e": [
      "forest"
    ]
  },
  {
    "j": "松",
    "e": [
      "pine"
    ]
  },
  {
    "j": "杉",
    "e": [
      "cedar"
    ]
  },
  {
    "j": "桜",
    "e": [
      "cherry"
    ]
  },
  {
    "j": "梅",
    "e": [
      "plum"
    ]
  },
  {
    "j": "梨",
    "e": [
      "pear"
    ]
  },
  {
    "j": "柿",
    "e": [
      "persimmon"
    ]
  },
  {
    "j": "栃",
    "e": [
      "horse chestnut"
    ]
  },
  {
    "j": "藤",
    "e": [
      "wisteria"
    ]
  },
  {
    "j": "桑",
    "e": [
      "mulberry"
    ]
  },
  {
    "j": "桃",
    "e": [
      "peach"
    ]
  },
  {
    "j": "柳",
    "e": [
      "willow"
    ]
  },
  {
    "j": "桂",
    "e": [
      "cinnamon tree"
    ]
  },
  {
    "j": "草",
    "e": [
      "grass"
    ]
  },
  {
    "j": "稲",
    "e": [
      "rice plant"
    ]
  },
  {
    "j": "麻",
    "e": [
      "hemp or flax"
    ]
  },
  {
    "j": "竹",
    "e": [
      "bamboo"
    ]
  },
  {
    "j": "葛",
    "e": [
      "vine"
    ]
  },
  {
    "j": "茨",
    "e": [
      "brier"
    ]
  },
  {
    "j": "菊",
    "e": [
      "chrysanthemum"
    ]
  },
  {
    "j": "栽",
    "e": [
      "cultivation of plants"
    ]
  },
  {
    "j": "藻",
    "e": [
      "algae, seaweed"
    ]
  },
  {
    "j": "茸",
    "e": [
      "mushroom"
    ]
  },
  {
    "j": "菌",
    "e": [
      "fungi or bacteria"
    ]
  },
  {
    "j": "根",
    "e": [
      "root"
    ]
  },
  {
    "j": "幹",
    "e": [
      "tree trunk"
    ]
  },
  {
    "j": "枝",
    "e": [
      "branch"
    ]
  },
  {
    "j": "葉",
    "e": [
      "leaf"
    ]
  },
  {
    "j": "花",
    "e": [
      "flower"
    ]
  },
  {
    "j": "芽",
    "e": [
      "bud"
    ]
  },
  {
    "j": "苗",
    "e": [
      "seedling"
    ]
  },
  {
    "j": "茎",
    "e": [
      "stem"
    ]
  },
  {
    "j": "人",
    "e": [
      "person"
    ]
  },
  {
    "j": "者",
    "e": [
      "person (usually with qualifier)"
    ]
  },
  {
    "j": "民",
    "e": [
      "people"
    ]
  },
  {
    "j": "男",
    "e": [
      "man"
    ]
  },
  {
    "j": "女",
    "e": [
      "woman"
    ]
  },
  {
    "j": "雄",
    "e": [
      "male"
    ]
  },
  {
    "j": "雌",
    "e": [
      "female"
    ]
  },
  {
    "j": "翁",
    "e": [
      "old man"
    ]
  },
  {
    "j": "婆",
    "e": [
      "old woman"
    ]
  },
  {
    "j": "嬢",
    "e": [
      "young lady"
    ]
  },
  {
    "j": "子",
    "e": [
      "child"
    ]
  },
  {
    "j": "児",
    "e": [
      "child"
    ]
  },
  {
    "j": "坊",
    "e": [
      "boy, sonny"
    ]
  },
  {
    "j": "郎",
    "e": [
      "son, boy"
    ]
  },
  {
    "j": "童",
    "e": [
      "juvenile"
    ]
  },
  {
    "j": "徒",
    "e": [
      "gang or junior"
    ]
  },
  {
    "j": "私",
    "e": [
      "I"
    ]
  },
  {
    "j": "僕",
    "e": [
      "I"
    ]
  },
  {
    "j": "俺",
    "e": [
      "I"
    ]
  },
  {
    "j": "彼",
    "e": [
      "he"
    ]
  },
  {
    "j": "君",
    "e": [
      "you"
    ]
  },
  {
    "j": "自",
    "e": [
      "oneself"
    ]
  },
  {
    "j": "己",
    "e": [
      "oneself"
    ]
  },
  {
    "j": "我",
    "e": [
      "self, ego"
    ]
  },
  {
    "j": "主",
    "e": [
      "master or husband"
    ]
  },
  {
    "j": "夫",
    "e": [
      "husband or man"
    ]
  },
  {
    "j": "妻",
    "e": [
      "wife"
    ]
  },
  {
    "j": "婦",
    "e": [
      "wife or lady"
    ]
  },
  {
    "j": "王",
    "e": [
      "king"
    ]
  },
  {
    "j": "皇",
    "e": [
      "emperor or sovereign"
    ]
  },
  {
    "j": "帝",
    "e": [
      "Mikado or emperor"
    ]
  },
  {
    "j": "姫",
    "e": [
      "princess"
    ]
  },
  {
    "j": "媛",
    "e": [
      "princess"
    ]
  },
  {
    "j": "妃",
    "e": [
      "princess, queen"
    ]
  },
  {
    "j": "后",
    "e": [
      "empress"
    ]
  },
  {
    "j": "伯",
    "e": [
      "earl, count"
    ]
  },
  {
    "j": "侯",
    "e": [
      "lord, marquis"
    ]
  },
  {
    "j": "爵",
    "e": [
      "noble rank"
    ]
  },
  {
    "j": "士",
    "e": [
      "man or gentleman"
    ]
  },
  {
    "j": "方",
    "e": [
      "honorable person"
    ]
  },
  {
    "j": "漢Han",
    "e": [
      "漢 honorable man or Han person"
    ]
  },
  {
    "j": "彦",
    "e": [
      "boy, high-status man"
    ]
  },
  {
    "j": "傑",
    "e": [
      "great man"
    ]
  },
  {
    "j": "紳",
    "e": [
      "gentleman"
    ]
  },
  {
    "j": "氏",
    "e": [
      "courtesy title"
    ]
  },
  {
    "j": "長",
    "e": [
      "leader"
    ]
  },
  {
    "j": "係",
    "e": [
      "person in charge"
    ]
  },
  {
    "j": "督",
    "e": [
      "supervisor"
    ]
  },
  {
    "j": "師",
    "e": [
      "expert"
    ]
  },
  {
    "j": "仲",
    "e": [
      "intermediary"
    ]
  },
  {
    "j": "使",
    "e": [
      "messenger"
    ]
  },
  {
    "j": "医",
    "e": [
      "doctor"
    ]
  },
  {
    "j": "友",
    "e": [
      "friend"
    ]
  },
  {
    "j": "僚",
    "e": [
      "colleague"
    ]
  },
  {
    "j": "輩",
    "e": [
      "fellow, comrade"
    ]
  },
  {
    "j": "客",
    "e": [
      "guest, customer"
    ]
  },
  {
    "j": "賓",
    "e": [
      "guest, VIP"
    ]
  },
  {
    "j": "隣",
    "e": [
      "neighbour"
    ]
  },
  {
    "j": "奴",
    "e": [
      "servant, fellow"
    ]
  },
  {
    "j": "隷",
    "e": [
      "underling"
    ]
  },
  {
    "j": "仙",
    "e": [
      "hermit"
    ]
  },
  {
    "j": "家",
    "e": [
      "family"
    ]
  },
  {
    "j": "族",
    "e": [
      "family"
    ]
  },
  {
    "j": "名",
    "e": [
      "name"
    ]
  },
  {
    "j": "父",
    "e": [
      "father"
    ]
  },
  {
    "j": "母",
    "e": [
      "mother"
    ]
  },
  {
    "j": "親",
    "e": [
      "parent"
    ]
  },
  {
    "j": "嫁",
    "e": [
      "wife, bride"
    ]
  },
  {
    "j": "娘",
    "e": [
      "daughter"
    ]
  },
  {
    "j": "弟",
    "e": [
      "younger brother"
    ]
  },
  {
    "j": "妹",
    "e": [
      "younger sister"
    ]
  },
  {
    "j": "兄",
    "e": [
      "older brother"
    ]
  },
  {
    "j": "姉",
    "e": [
      "older sister"
    ]
  },
  {
    "j": "爺",
    "e": [
      "grandfather"
    ]
  },
  {
    "j": "婆",
    "e": [
      "grandmother"
    ]
  },
  {
    "j": "祖",
    "e": [
      "ancestor"
    ]
  },
  {
    "j": "孫",
    "e": [
      "grandchild"
    ]
  },
  {
    "j": "叔",
    "e": [
      "aunt, uncle"
    ]
  },
  {
    "j": "伯",
    "e": [
      "aunt, uncle"
    ]
  },
  {
    "j": "甥",
    "e": [
      "nephew"
    ]
  },
  {
    "j": "姪",
    "e": [
      "niece"
    ]
  },
  {
    "j": "婿",
    "e": [
      "son-in-law, bridegroom"
    ]
  },
  {
    "j": "昆",
    "e": [
      "descendants"
    ]
  },
  {
    "j": "戚",
    "e": [
      "relatives"
    ]
  },
  {
    "j": "婚",
    "e": [
      "marry"
    ]
  },
  {
    "j": "姻",
    "e": [
      "matrimony"
    ]
  },
  {
    "j": "嫡",
    "e": [
      "legitimate wife/family"
    ]
  },
  {
    "j": "寡",
    "e": [
      "widow"
    ]
  },
  {
    "j": "国",
    "e": [
      "country"
    ]
  },
  {
    "j": "社",
    "e": [
      "company"
    ]
  },
  {
    "j": "団",
    "e": [
      "group"
    ]
  },
  {
    "j": "派",
    "e": [
      "faction, group"
    ]
  },
  {
    "j": "組",
    "e": [
      "association, assemble"
    ]
  },
  {
    "j": "群",
    "e": [
      "flock, crowd"
    ]
  },
  {
    "j": "身",
    "e": [
      "body"
    ]
  },
  {
    "j": "体",
    "e": [
      "body"
    ]
  },
  {
    "j": "肉",
    "e": [
      "flesh"
    ]
  },
  {
    "j": "血",
    "e": [
      "blood"
    ]
  },
  {
    "j": "脈",
    "e": [
      "vein"
    ]
  },
  {
    "j": "筋",
    "e": [
      "muscles"
    ]
  },
  {
    "j": "骨",
    "e": [
      "bone"
    ]
  },
  {
    "j": "髄",
    "e": [
      "marrow"
    ]
  },
  {
    "j": "節",
    "e": [
      "joint"
    ]
  },
  {
    "j": "皮",
    "e": [
      "skin"
    ]
  },
  {
    "j": "膚",
    "e": [
      "skin"
    ]
  },
  {
    "j": "肌",
    "e": [
      "skin"
    ]
  },
  {
    "j": "皺",
    "e": [
      "wrinkle"
    ]
  },
  {
    "j": "腺",
    "e": [
      "gland"
    ]
  },
  {
    "j": "頭",
    "e": [
      "head"
    ]
  },
  {
    "j": "脳",
    "e": [
      "brain"
    ]
  },
  {
    "j": "髪",
    "e": [
      "hair"
    ]
  },
  {
    "j": "顔",
    "e": [
      "face"
    ]
  },
  {
    "j": "髭",
    "e": [
      "beard"
    ]
  },
  {
    "j": "額",
    "e": [
      "forehead"
    ]
  },
  {
    "j": "耳",
    "e": [
      "ear"
    ]
  },
  {
    "j": "目",
    "e": [
      "eye"
    ]
  },
  {
    "j": "眼",
    "e": [
      "eyeball"
    ]
  },
  {
    "j": "眉",
    "e": [
      "eyebrow"
    ]
  },
  {
    "j": "瞳",
    "e": [
      "pupil"
    ]
  },
  {
    "j": "鼻",
    "e": [
      "nose"
    ]
  },
  {
    "j": "顎",
    "e": [
      "jaw"
    ]
  },
  {
    "j": "口",
    "e": [
      "mouth"
    ]
  },
  {
    "j": "唇",
    "e": [
      "lips"
    ]
  },
  {
    "j": "歯",
    "e": [
      "tooth"
    ]
  },
  {
    "j": "舌",
    "e": [
      "tongue"
    ]
  },
  {
    "j": "頬",
    "e": [
      "cheek"
    ]
  },
  {
    "j": "頤",
    "e": [
      "chin"
    ]
  },
  {
    "j": "喉",
    "e": [
      "throat"
    ]
  },
  {
    "j": "咽",
    "e": [
      "throat"
    ]
  },
  {
    "j": "首",
    "e": [
      "neck"
    ]
  },
  {
    "j": "胴",
    "e": [
      "torso"
    ]
  },
  {
    "j": "背",
    "e": [
      "back"
    ]
  },
  {
    "j": "脊",
    "e": [
      "backbone"
    ]
  },
  {
    "j": "呂",
    "e": [
      "backbone"
    ]
  },
  {
    "j": "椎",
    "e": [
      "backbone"
    ]
  },
  {
    "j": "肋",
    "e": [
      "rib"
    ]
  },
  {
    "j": "胸",
    "e": [
      "chest"
    ]
  },
  {
    "j": "腹",
    "e": [
      "stomach"
    ]
  },
  {
    "j": "胃",
    "e": [
      "stomach"
    ]
  },
  {
    "j": "臍",
    "e": [
      "navel"
    ]
  },
  {
    "j": "腰",
    "e": [
      "waist"
    ]
  },
  {
    "j": "臓",
    "e": [
      "entrails"
    ]
  },
  {
    "j": "腸",
    "e": [
      "intestines"
    ]
  },
  {
    "j": "心",
    "e": [
      "heart"
    ]
  },
  {
    "j": "肺",
    "e": [
      "lung"
    ]
  },
  {
    "j": "肝",
    "e": [
      "liver"
    ]
  },
  {
    "j": "膵",
    "e": [
      "pancreas"
    ]
  },
  {
    "j": "腎",
    "e": [
      "kidney"
    ]
  },
  {
    "j": "胆",
    "e": [
      "gall bladder"
    ]
  },
  {
    "j": "肛",
    "e": [
      "anus"
    ]
  },
  {
    "j": "膣",
    "e": [
      "vagina"
    ]
  },
  {
    "j": "肢",
    "e": [
      "limb"
    ]
  },
  {
    "j": "腕",
    "e": [
      "arm"
    ]
  },
  {
    "j": "肩",
    "e": [
      "shoulder"
    ]
  },
  {
    "j": "脇",
    "e": [
      "armpit"
    ]
  },
  {
    "j": "肘",
    "e": [
      "elbow"
    ]
  },
  {
    "j": "手",
    "e": [
      "hand"
    ]
  },
  {
    "j": "拳",
    "e": [
      "fist"
    ]
  },
  {
    "j": "指",
    "e": [
      "finger"
    ]
  },
  {
    "j": "爪",
    "e": [
      "nail"
    ]
  },
  {
    "j": "掌",
    "e": [
      "palm"
    ]
  },
  {
    "j": "尻",
    "e": [
      "buttocks"
    ]
  },
  {
    "j": "股",
    "e": [
      "thighs"
    ]
  },
  {
    "j": "脚",
    "e": [
      "leg"
    ]
  },
  {
    "j": "足",
    "e": [
      "leg, foot"
    ]
  },
  {
    "j": "膝",
    "e": [
      "knee"
    ]
  },
  {
    "j": "踝",
    "e": [
      "ankle"
    ]
  },
  {
    "j": "踵",
    "e": [
      "heel"
    ]
  },
  {
    "j": "汗",
    "e": [
      "sweat"
    ]
  },
  {
    "j": "泪",
    "e": [
      "tear"
    ]
  },
  {
    "j": "涙",
    "e": [
      "tear"
    ]
  },
  {
    "j": "唾",
    "e": [
      "saliva"
    ]
  },
  {
    "j": "精",
    "e": [
      "sperm"
    ]
  },
  {
    "j": "尿",
    "e": [
      "urine"
    ]
  },
  {
    "j": "便",
    "e": [
      "faeces"
    ]
  },
  {
    "j": "胎",
    "e": [
      "foetus"
    ]
  },
  {
    "j": "妊",
    "e": [
      "pregnant"
    ]
  },
  {
    "j": "娠",
    "e": [
      "pregnant"
    ]
  },
  {
    "j": "生",
    "e": [
      "birth"
    ]
  },
  {
    "j": "産",
    "e": [
      "give birth"
    ]
  },
  {
    "j": "哺",
    "e": [
      "suckle"
    ]
  },
  {
    "j": "息",
    "e": [
      "breath"
    ]
  },
  {
    "j": "寝",
    "e": [
      "sleep"
    ]
  },
  {
    "j": "眠",
    "e": [
      "sleep"
    ]
  },
  {
    "j": "睡",
    "e": [
      "sleep"
    ]
  },
  {
    "j": "夢",
    "e": [
      "dream"
    ]
  },
  {
    "j": "生",
    "e": [
      "life"
    ]
  },
  {
    "j": "死",
    "e": [
      "death"
    ]
  },
  {
    "j": "健",
    "e": [
      "healthy"
    ]
  },
  {
    "j": "康",
    "e": [
      "healthy"
    ]
  },
  {
    "j": "力",
    "e": [
      "strength"
    ]
  },
  {
    "j": "病",
    "e": [
      "illness"
    ]
  },
  {
    "j": "症",
    "e": [
      "disease"
    ]
  },
  {
    "j": "疾",
    "e": [
      "disease"
    ]
  },
  {
    "j": "患",
    "e": [
      "sick"
    ]
  },
  {
    "j": "疫",
    "e": [
      "epidemic"
    ]
  },
  {
    "j": "骸",
    "e": [
      "corpse"
    ]
  },
  {
    "j": "痛",
    "e": [
      "pain"
    ]
  },
  {
    "j": "疲",
    "e": [
      "tired"
    ]
  },
  {
    "j": "休",
    "e": [
      "rest"
    ]
  },
  {
    "j": "痩",
    "e": [
      "weight loss"
    ]
  },
  {
    "j": "瘍",
    "e": [
      "ulcer"
    ]
  },
  {
    "j": "痘",
    "e": [
      "pox"
    ]
  },
  {
    "j": "痢",
    "e": [
      "diarrhoea"
    ]
  },
  {
    "j": "癌",
    "e": [
      "cancer"
    ]
  },
  {
    "j": "傷",
    "e": [
      "wound"
    ]
  },
  {
    "j": "痕",
    "e": [
      "scar"
    ]
  },
  {
    "j": "医",
    "e": [
      "medicine, doctor"
    ]
  },
  {
    "j": "療",
    "e": [
      "heal"
    ]
  },
  {
    "j": "癒",
    "e": [
      "heal"
    ]
  },
  {
    "j": "治",
    "e": [
      "cure"
    ]
  },
  {
    "j": "剤",
    "e": [
      "medicine"
    ]
  },
  {
    "j": "錠",
    "e": [
      "pill"
    ]
  },
  {
    "j": "薬",
    "e": [
      "drug"
    ]
  },
  {
    "j": "立",
    "e": [
      "stand up"
    ]
  },
  {
    "j": "走",
    "e": [
      "run"
    ]
  },
  {
    "j": "座",
    "e": [
      "sit"
    ]
  },
  {
    "j": "踊",
    "e": [
      "jump"
    ]
  },
  {
    "j": "歩",
    "e": [
      "walk"
    ]
  },
  {
    "j": "泳",
    "e": [
      "swim"
    ]
  },
  {
    "j": "止",
    "e": [
      "stop"
    ]
  },
  {
    "j": "情",
    "e": [
      "emotion"
    ]
  },
  {
    "j": "感",
    "e": [
      "feeling, emotion"
    ]
  },
  {
    "j": "気",
    "e": [
      "feeling, mood"
    ]
  },
  {
    "j": "愛",
    "e": [
      "love"
    ]
  },
  {
    "j": "恋",
    "e": [
      "love"
    ]
  },
  {
    "j": "慕",
    "e": [
      "adoration"
    ]
  },
  {
    "j": "崇",
    "e": [
      "reverence, adoration"
    ]
  },
  {
    "j": "恭",
    "e": [
      "respect"
    ]
  },
  {
    "j": "敬",
    "e": [
      "respect"
    ]
  },
  {
    "j": "慈",
    "e": [
      "affection, benevolence"
    ]
  },
  {
    "j": "憎",
    "e": [
      "hate"
    ]
  },
  {
    "j": "好",
    "e": [
      "like"
    ]
  },
  {
    "j": "嫌",
    "e": [
      "dislike"
    ]
  },
  {
    "j": "蔑",
    "e": [
      "contempt"
    ]
  },
  {
    "j": "恐",
    "e": [
      "fear or anxiety"
    ]
  },
  {
    "j": "虞",
    "e": [
      "fear or anxiety"
    ]
  },
  {
    "j": "怖",
    "e": [
      "fear or anxiety"
    ]
  },
  {
    "j": "畏",
    "e": [
      "fear or anxiety"
    ]
  },
  {
    "j": "慄",
    "e": [
      "fear"
    ]
  },
  {
    "j": "惧",
    "e": [
      "apprehension"
    ]
  },
  {
    "j": "悲",
    "e": [
      "sadness"
    ]
  },
  {
    "j": "哀",
    "e": [
      "sadness or pity"
    ]
  },
  {
    "j": "憂",
    "e": [
      "sadness, anxiety"
    ]
  },
  {
    "j": "煩",
    "e": [
      "anxiety, annoyance"
    ]
  },
  {
    "j": "愁",
    "e": [
      "melancholy"
    ]
  },
  {
    "j": "鬱",
    "e": [
      "melancholy"
    ]
  },
  {
    "j": "惜",
    "e": [
      "regret"
    ]
  },
  {
    "j": "憾",
    "e": [
      "regret"
    ]
  },
  {
    "j": "悔",
    "e": [
      "remorse"
    ]
  },
  {
    "j": "懐",
    "e": [
      "yearning"
    ]
  },
  {
    "j": "憧",
    "e": [
      "yearning, adoration"
    ]
  },
  {
    "j": "憬",
    "e": [
      "yearning"
    ]
  },
  {
    "j": "戚",
    "e": [
      "grief"
    ]
  },
  {
    "j": "恨",
    "e": [
      "resentment"
    ]
  },
  {
    "j": "怨",
    "e": [
      "resentment"
    ]
  },
  {
    "j": "慨",
    "e": [
      "indignation, resentment"
    ]
  },
  {
    "j": "寂",
    "e": [
      "loneliness"
    ]
  },
  {
    "j": "楽",
    "e": [
      "fun"
    ]
  },
  {
    "j": "愉",
    "e": [
      "fun"
    ]
  },
  {
    "j": "娯",
    "e": [
      "fun"
    ]
  },
  {
    "j": "幸",
    "e": [
      "happiness"
    ]
  },
  {
    "j": "嬉",
    "e": [
      "happiness"
    ]
  },
  {
    "j": "喜",
    "e": [
      "joy"
    ]
  },
  {
    "j": "悦",
    "e": [
      "joy"
    ]
  },
  {
    "j": "慶",
    "e": [
      "joy"
    ]
  },
  {
    "j": "歓",
    "e": [
      "joy"
    ]
  },
  {
    "j": "快",
    "e": [
      "pleasure"
    ]
  },
  {
    "j": "笑",
    "e": [
      "laughter"
    ]
  },
  {
    "j": "疑",
    "e": [
      "doubt or suspicion"
    ]
  },
  {
    "j": "迷",
    "e": [
      "doubt"
    ]
  },
  {
    "j": "迷",
    "e": [
      "confusion"
    ]
  },
  {
    "j": "紛",
    "e": [
      "confusion"
    ]
  },
  {
    "j": "惑",
    "e": [
      "bewilderment"
    ]
  },
  {
    "j": "慌",
    "e": [
      "disconcertion"
    ]
  },
  {
    "j": "驚",
    "e": [
      "surprise"
    ]
  },
  {
    "j": "欲",
    "e": [
      "desire"
    ]
  },
  {
    "j": "怒",
    "e": [
      "anger"
    ]
  },
  {
    "j": "激",
    "e": [
      "violent excitement"
    ]
  },
  {
    "j": "暴",
    "e": [
      "violent rage"
    ]
  },
  {
    "j": "憤",
    "e": [
      "indignation"
    ]
  },
  {
    "j": "傲",
    "e": [
      "pride"
    ]
  },
  {
    "j": "恥",
    "e": [
      "shame"
    ]
  },
  {
    "j": "羞",
    "e": [
      "shame"
    ]
  },
  {
    "j": "妬",
    "e": [
      "envy"
    ]
  },
  {
    "j": "羨",
    "e": [
      "envy"
    ]
  },
  {
    "j": "嫉",
    "e": [
      "envy"
    ]
  },
  {
    "j": "見",
    "e": [
      "see"
    ]
  },
  {
    "j": "聞",
    "e": [
      "hear"
    ]
  },
  {
    "j": "聴",
    "e": [
      "listen"
    ]
  },
  {
    "j": "音",
    "e": [
      "sound"
    ]
  },
  {
    "j": "静",
    "e": [
      "quiet"
    ]
  },
  {
    "j": "味",
    "e": [
      "taste, flavour"
    ]
  },
  {
    "j": "辣",
    "e": [
      "bitter"
    ]
  },
  {
    "j": "辛",
    "e": [
      "pungent"
    ]
  },
  {
    "j": "触",
    "e": [
      "touch, feel"
    ]
  },
  {
    "j": "嗅",
    "e": [
      "smell"
    ]
  },
  {
    "j": "芳",
    "e": [
      "fragrant"
    ]
  },
  {
    "j": "匂",
    "e": [
      "fragrant"
    ]
  },
  {
    "j": "香",
    "e": [
      "pleasant smell"
    ]
  },
  {
    "j": "臭",
    "e": [
      "bad smell"
    ]
  },
  {
    "j": "盲",
    "e": [
      "blind"
    ]
  },
  {
    "j": "思",
    "e": [
      "think"
    ]
  },
  {
    "j": "考",
    "e": [
      "think"
    ]
  },
  {
    "j": "正",
    "e": [
      "correct"
    ]
  },
  {
    "j": "良",
    "e": [
      "good"
    ]
  },
  {
    "j": "善",
    "e": [
      "good"
    ]
  },
  {
    "j": "悪",
    "e": [
      "bad"
    ]
  },
  {
    "j": "理",
    "e": [
      "reason"
    ]
  },
  {
    "j": "食",
    "e": [
      "eat, meal"
    ]
  },
  {
    "j": "飲",
    "e": [
      "drink"
    ]
  },
  {
    "j": "米",
    "e": [
      "rice"
    ]
  },
  {
    "j": "飯",
    "e": [
      "cooked rice, meal"
    ]
  },
  {
    "j": "餅",
    "e": [
      "rice cake"
    ]
  },
  {
    "j": "麦",
    "e": [
      "wheat or barley"
    ]
  },
  {
    "j": "粒",
    "e": [
      "grain"
    ]
  },
  {
    "j": "穀",
    "e": [
      "cereal"
    ]
  },
  {
    "j": "穂",
    "e": [
      "ear of grain"
    ]
  },
  {
    "j": "果",
    "e": [
      "fruit"
    ]
  },
  {
    "j": "実",
    "e": [
      "fruit"
    ]
  },
  {
    "j": "菜",
    "e": [
      "vegetable"
    ]
  },
  {
    "j": "豆",
    "e": [
      "bean"
    ]
  },
  {
    "j": "麺",
    "e": [
      "noodles"
    ]
  },
  {
    "j": "芋",
    "e": [
      "potato"
    ]
  },
  {
    "j": "粉",
    "e": [
      "flour"
    ]
  },
  {
    "j": "卵",
    "e": [
      "egg"
    ]
  },
  {
    "j": "糖",
    "e": [
      "sugar"
    ]
  },
  {
    "j": "肉",
    "e": [
      "meat"
    ]
  },
  {
    "j": "乳",
    "e": [
      "milk"
    ]
  },
  {
    "j": "酪",
    "e": [
      "dairy products"
    ]
  },
  {
    "j": "蜜",
    "e": [
      "honey"
    ]
  },
  {
    "j": "菓",
    "e": [
      "confectionery"
    ]
  },
  {
    "j": "栗",
    "e": [
      "chestnut"
    ]
  },
  {
    "j": "酒",
    "e": [
      "alcoholic drink"
    ]
  },
  {
    "j": "酎",
    "e": [
      "sake"
    ]
  },
  {
    "j": "酌",
    "e": [
      "serve alcohol"
    ]
  },
  {
    "j": "酢",
    "e": [
      "vinegar"
    ]
  },
  {
    "j": "漬",
    "e": [
      "pickle"
    ]
  },
  {
    "j": "汁",
    "e": [
      "juice, soup"
    ]
  },
  {
    "j": "茶",
    "e": [
      "tea"
    ]
  },
  {
    "j": "炊",
    "e": [
      "cook"
    ]
  },
  {
    "j": "焼",
    "e": [
      "bake"
    ]
  },
  {
    "j": "煎",
    "e": [
      "roast, boil"
    ]
  },
  {
    "j": "蒸",
    "e": [
      "steam"
    ]
  },
  {
    "j": "醸",
    "e": [
      "brew"
    ]
  },
  {
    "j": "揚",
    "e": [
      "fry"
    ]
  },
  {
    "j": "丼",
    "e": [
      "bowl of food"
    ]
  },
  {
    "j": "箸",
    "e": [
      "chopsticks"
    ]
  },
  {
    "j": "鮨sushi",
    "e": [
      "鮨 sushi"
    ]
  },
  {
    "j": "村",
    "e": [
      "village"
    ]
  },
  {
    "j": "町",
    "e": [
      "town"
    ]
  },
  {
    "j": "市",
    "e": [
      "city"
    ]
  },
  {
    "j": "京",
    "e": [
      "capital city"
    ]
  },
  {
    "j": "都",
    "e": [
      "metropolis"
    ]
  },
  {
    "j": "畿",
    "e": [
      "capital"
    ]
  },
  {
    "j": "街",
    "e": [
      "street, city district"
    ]
  },
  {
    "j": "建",
    "e": [
      "build"
    ]
  },
  {
    "j": "家",
    "e": [
      "house"
    ]
  },
  {
    "j": "宅",
    "e": [
      "home"
    ]
  },
  {
    "j": "屋",
    "e": [
      "roof, house, shop"
    ]
  },
  {
    "j": "店",
    "e": [
      "shop"
    ]
  },
  {
    "j": "荘",
    "e": [
      "villa"
    ]
  },
  {
    "j": "亭",
    "e": [
      "pavilion"
    ]
  },
  {
    "j": "園",
    "e": [
      "garden"
    ]
  },
  {
    "j": "芝",
    "e": [
      "lawn, turf"
    ]
  },
  {
    "j": "庭",
    "e": [
      "garden, courtyard"
    ]
  },
  {
    "j": "室",
    "e": [
      "room"
    ]
  },
  {
    "j": "房",
    "e": [
      "room"
    ]
  },
  {
    "j": "廊",
    "e": [
      "corridor"
    ]
  },
  {
    "j": "壁",
    "e": [
      "wall"
    ]
  },
  {
    "j": "戸",
    "e": [
      "door"
    ]
  },
  {
    "j": "扉",
    "e": [
      "door"
    ]
  },
  {
    "j": "窓",
    "e": [
      "window"
    ]
  },
  {
    "j": "棚",
    "e": [
      "shelf"
    ]
  },
  {
    "j": "門",
    "e": [
      "gate"
    ]
  },
  {
    "j": "垣",
    "e": [
      "fence"
    ]
  },
  {
    "j": "塀",
    "e": [
      "wall, fence"
    ]
  },
  {
    "j": "柵",
    "e": [
      "fence"
    ]
  },
  {
    "j": "寮",
    "e": [
      "dormitory"
    ]
  },
  {
    "j": "蔵",
    "e": [
      "storehouse"
    ]
  },
  {
    "j": "庫",
    "e": [
      "storage room"
    ]
  },
  {
    "j": "倉",
    "e": [
      "warehouse"
    ]
  },
  {
    "j": "舎",
    "e": [
      "building"
    ]
  },
  {
    "j": "館",
    "e": [
      "public building"
    ]
  },
  {
    "j": "閣",
    "e": [
      "imposing building"
    ]
  },
  {
    "j": "宮",
    "e": [
      "palace"
    ]
  },
  {
    "j": "殿",
    "e": [
      "hall, palace"
    ]
  },
  {
    "j": "堂",
    "e": [
      "hall"
    ]
  },
  {
    "j": "楼",
    "e": [
      "tower"
    ]
  },
  {
    "j": "塔",
    "e": [
      "tower"
    ]
  },
  {
    "j": "城",
    "e": [
      "castle"
    ]
  },
  {
    "j": "塁",
    "e": [
      "base, fort"
    ]
  },
  {
    "j": "獄",
    "e": [
      "prison"
    ]
  },
  {
    "j": "宿",
    "e": [
      "inn"
    ]
  },
  {
    "j": "駅",
    "e": [
      "station"
    ]
  },
  {
    "j": "港",
    "e": [
      "harbour"
    ]
  },
  {
    "j": "津",
    "e": [
      "harbour"
    ]
  },
  {
    "j": "橋",
    "e": [
      "bridge"
    ]
  },
  {
    "j": "碑",
    "e": [
      "monument"
    ]
  },
  {
    "j": "桟",
    "e": [
      "wooden structure"
    ]
  },
  {
    "j": "桁",
    "e": [
      "beam, column"
    ]
  },
  {
    "j": "柱",
    "e": [
      "pillar"
    ]
  },
  {
    "j": "棟",
    "e": [
      "ridgepole"
    ]
  },
  {
    "j": "壇",
    "e": [
      "podium"
    ]
  },
  {
    "j": "台",
    "e": [
      "pedestal"
    ]
  },
  {
    "j": "井",
    "e": [
      "well"
    ]
  },
  {
    "j": "炉",
    "e": [
      "fireplace, hearth"
    ]
  },
  {
    "j": "道",
    "e": [
      "path or road"
    ]
  },
  {
    "j": "路",
    "e": [
      "path or road"
    ]
  },
  {
    "j": "途",
    "e": [
      "way, route"
    ]
  },
  {
    "j": "岐",
    "e": [
      "fork in the road"
    ]
  },
  {
    "j": "辻",
    "e": [
      "crossroads"
    ]
  },
  {
    "j": "車",
    "e": [
      "vehicle, wheel"
    ]
  },
  {
    "j": "軸",
    "e": [
      "axle"
    ]
  },
  {
    "j": "機",
    "e": [
      "machine"
    ]
  },
  {
    "j": "械",
    "e": [
      "contraption"
    ]
  },
  {
    "j": "船",
    "e": [
      "boat"
    ]
  },
  {
    "j": "艇",
    "e": [
      "boat"
    ]
  },
  {
    "j": "舟",
    "e": [
      "small boat"
    ]
  },
  {
    "j": "舶",
    "e": [
      "oceangoing ship"
    ]
  },
  {
    "j": "舷",
    "e": [
      "side of a ship"
    ]
  },
  {
    "j": "乗",
    "e": [
      "ride, board"
    ]
  },
  {
    "j": "搭",
    "e": [
      "board, load"
    ]
  },
  {
    "j": "力",
    "e": [
      "power"
    ]
  },
  {
    "j": "布",
    "e": [
      "cloth"
    ]
  },
  {
    "j": "巾",
    "e": [
      "cloth, towel"
    ]
  },
  {
    "j": "衣",
    "e": [
      "garment"
    ]
  },
  {
    "j": "服",
    "e": [
      "clothes"
    ]
  },
  {
    "j": "装",
    "e": [
      "attire"
    ]
  },
  {
    "j": "絹",
    "e": [
      "silk"
    ]
  },
  {
    "j": "袖",
    "e": [
      "sleeve"
    ]
  },
  {
    "j": "裾",
    "e": [
      "hem, cuff"
    ]
  },
  {
    "j": "襟",
    "e": [
      "collar"
    ]
  },
  {
    "j": "帯",
    "e": [
      "belt"
    ]
  },
  {
    "j": "靴",
    "e": [
      "shoes"
    ]
  },
  {
    "j": "履",
    "e": [
      "footwear"
    ]
  },
  {
    "j": "帽",
    "e": [
      "hat"
    ]
  },
  {
    "j": "着",
    "e": [
      "wear"
    ]
  },
  {
    "j": "糸",
    "e": [
      "thread"
    ]
  },
  {
    "j": "縫",
    "e": [
      "sew"
    ]
  },
  {
    "j": "織",
    "e": [
      "weave"
    ]
  },
  {
    "j": "紡",
    "e": [
      "spin (yarn)"
    ]
  },
  {
    "j": "綿",
    "e": [
      "cotton"
    ]
  },
  {
    "j": "錦",
    "e": [
      "brocade"
    ]
  },
  {
    "j": "品",
    "e": [
      "article"
    ]
  },
  {
    "j": "器",
    "e": [
      "vessel"
    ]
  },
  {
    "j": "鉢",
    "e": [
      "bowl"
    ]
  },
  {
    "j": "丼",
    "e": [
      "bowl"
    ]
  },
  {
    "j": "杯",
    "e": [
      "cup"
    ]
  },
  {
    "j": "鍋",
    "e": [
      "pot"
    ]
  },
  {
    "j": "釜",
    "e": [
      "kettle"
    ]
  },
  {
    "j": "皿",
    "e": [
      "plate, dish"
    ]
  },
  {
    "j": "板",
    "e": [
      "board, plate"
    ]
  },
  {
    "j": "盤",
    "e": [
      "disk, board"
    ]
  },
  {
    "j": "盆",
    "e": [
      "basin, tray"
    ]
  },
  {
    "j": "瓶",
    "e": [
      "bottle, jar"
    ]
  },
  {
    "j": "缶",
    "e": [
      "tin can"
    ]
  },
  {
    "j": "箸",
    "e": [
      "chopsticks"
    ]
  },
  {
    "j": "蓋",
    "e": [
      "lid"
    ]
  },
  {
    "j": "栓",
    "e": [
      "stopper, plug"
    ]
  },
  {
    "j": "卓",
    "e": [
      "table"
    ]
  },
  {
    "j": "椅",
    "e": [
      "chair"
    ]
  },
  {
    "j": "机",
    "e": [
      "desk"
    ]
  },
  {
    "j": "床",
    "e": [
      "bed"
    ]
  },
  {
    "j": "膳",
    "e": [
      "tray, small table"
    ]
  },
  {
    "j": "箱",
    "e": [
      "box"
    ]
  },
  {
    "j": "灯",
    "e": [
      "lamp"
    ]
  },
  {
    "j": "袋",
    "e": [
      "bag"
    ]
  },
  {
    "j": "俵",
    "e": [
      "straw sack, bag"
    ]
  },
  {
    "j": "籠",
    "e": [
      "basket"
    ]
  },
  {
    "j": "扇",
    "e": [
      "fan"
    ]
  },
  {
    "j": "枕",
    "e": [
      "pillow"
    ]
  },
  {
    "j": "幕",
    "e": [
      "curtain"
    ]
  },
  {
    "j": "帆",
    "e": [
      "sail"
    ]
  },
  {
    "j": "畳",
    "e": [
      "tatami mat"
    ]
  },
  {
    "j": "傘",
    "e": [
      "umbrella"
    ]
  },
  {
    "j": "磁",
    "e": [
      "porcelain"
    ]
  },
  {
    "j": "陶",
    "e": [
      "pottery"
    ]
  },
  {
    "j": "瓦",
    "e": [
      "tile"
    ]
  },
  {
    "j": "紙",
    "e": [
      "paper"
    ]
  },
  {
    "j": "箋",
    "e": [
      "paper"
    ]
  },
  {
    "j": "革",
    "e": [
      "leather"
    ]
  },
  {
    "j": "塗",
    "e": [
      "paint"
    ]
  },
  {
    "j": "漆",
    "e": [
      "lacquer"
    ]
  },
  {
    "j": "棒",
    "e": [
      "rod"
    ]
  },
  {
    "j": "維",
    "e": [
      "fibre"
    ]
  },
  {
    "j": "網",
    "e": [
      "net"
    ]
  },
  {
    "j": "索",
    "e": [
      "cord"
    ]
  },
  {
    "j": "縄",
    "e": [
      "rope"
    ]
  },
  {
    "j": "綱",
    "e": [
      "rope"
    ]
  },
  {
    "j": "弦",
    "e": [
      "string"
    ]
  },
  {
    "j": "針",
    "e": [
      "needle"
    ]
  },
  {
    "j": "鎌",
    "e": [
      "sickle"
    ]
  },
  {
    "j": "管",
    "e": [
      "pipe"
    ]
  },
  {
    "j": "槽",
    "e": [
      "tank"
    ]
  },
  {
    "j": "鎖",
    "e": [
      "chain"
    ]
  },
  {
    "j": "串",
    "e": [
      "skewer"
    ]
  },
  {
    "j": "具",
    "e": [
      "tool"
    ]
  },
  {
    "j": "鍵",
    "e": [
      "key"
    ]
  },
  {
    "j": "錠",
    "e": [
      "lock"
    ]
  },
  {
    "j": "鈴",
    "e": [
      "bell"
    ]
  },
  {
    "j": "鐘",
    "e": [
      "bell"
    ]
  },
  {
    "j": "鋳",
    "e": [
      "casting"
    ]
  },
  {
    "j": "鏡",
    "e": [
      "mirror"
    ]
  },
  {
    "j": "棺",
    "e": [
      "coffin"
    ]
  },
  {
    "j": "窯",
    "e": [
      "stove, kiln"
    ]
  },
  {
    "j": "臼",
    "e": [
      "millstone, mortar"
    ]
  },
  {
    "j": "錘",
    "e": [
      "spindle, plumb"
    ]
  },
  {
    "j": "枢",
    "e": [
      "hinge, pivot"
    ]
  },
  {
    "j": "斤",
    "e": [
      "axe"
    ]
  },
  {
    "j": "鈎fish hook",
    "e": [
      "鈎 fish hook"
    ]
  },
  {
    "j": "金",
    "e": [
      "money or gold"
    ]
  },
  {
    "j": "銭",
    "e": [
      "coin"
    ]
  },
  {
    "j": "札",
    "e": [
      "banknote"
    ]
  },
  {
    "j": "円",
    "e": [
      "yen"
    ]
  },
  {
    "j": "幣",
    "e": [
      "currency"
    ]
  },
  {
    "j": "財",
    "e": [
      "wealth"
    ]
  },
  {
    "j": "富",
    "e": [
      "rich"
    ]
  },
  {
    "j": "買",
    "e": [
      "buy"
    ]
  },
  {
    "j": "購",
    "e": [
      "purchase"
    ]
  },
  {
    "j": "売",
    "e": [
      "sell"
    ]
  },
  {
    "j": "業",
    "e": [
      "business, industry"
    ]
  },
  {
    "j": "商",
    "e": [
      "trade"
    ]
  },
  {
    "j": "貿",
    "e": [
      "trade"
    ]
  },
  {
    "j": "販",
    "e": [
      "marketing"
    ]
  },
  {
    "j": "卸",
    "e": [
      "wholesale"
    ]
  },
  {
    "j": "払",
    "e": [
      "pay"
    ]
  },
  {
    "j": "貝ancient Chinese currency",
    "e": [
      "貝 cowry (ancient Chinese currency)"
    ]
  },
  {
    "j": "貨",
    "e": [
      "goods, property"
    ]
  },
  {
    "j": "宝",
    "e": [
      "treasure, wealth"
    ]
  },
  {
    "j": "産",
    "e": [
      "product"
    ]
  },
  {
    "j": "工",
    "e": [
      "manufacture"
    ]
  },
  {
    "j": "価",
    "e": [
      "price"
    ]
  },
  {
    "j": "値",
    "e": [
      "price"
    ]
  },
  {
    "j": "高",
    "e": [
      "expensive"
    ]
  },
  {
    "j": "安",
    "e": [
      "cheap"
    ]
  },
  {
    "j": "廉",
    "e": [
      "cheap"
    ]
  },
  {
    "j": "資",
    "e": [
      "capital"
    ]
  },
  {
    "j": "賃",
    "e": [
      "fee or wages"
    ]
  },
  {
    "j": "料",
    "e": [
      "fee"
    ]
  },
  {
    "j": "費",
    "e": [
      "expense"
    ]
  },
  {
    "j": "営",
    "e": [
      "management"
    ]
  },
  {
    "j": "職",
    "e": [
      "employment"
    ]
  },
  {
    "j": "働",
    "e": [
      "work"
    ]
  },
  {
    "j": "稼",
    "e": [
      "work, earn"
    ]
  },
  {
    "j": "給",
    "e": [
      "salary"
    ]
  },
  {
    "j": "俸",
    "e": [
      "salary"
    ]
  },
  {
    "j": "償",
    "e": [
      "recompense"
    ]
  },
  {
    "j": "債",
    "e": [
      "debt, bond"
    ]
  },
  {
    "j": "貯",
    "e": [
      "savings"
    ]
  },
  {
    "j": "税",
    "e": [
      "tax"
    ]
  },
  {
    "j": "租",
    "e": [
      "tax"
    ]
  },
  {
    "j": "賦",
    "e": [
      "levy, instalment"
    ]
  },
  {
    "j": "賄",
    "e": [
      "bribe"
    ]
  },
  {
    "j": "賂",
    "e": [
      "bribe"
    ]
  },
  {
    "j": "賭",
    "e": [
      "gamble"
    ]
  },
  {
    "j": "芸",
    "e": [
      "art"
    ]
  },
  {
    "j": "絵",
    "e": [
      "picture, painting"
    ]
  },
  {
    "j": "画",
    "e": [
      "picture"
    ]
  },
  {
    "j": "楽",
    "e": [
      "music"
    ]
  },
  {
    "j": "曲",
    "e": [
      "musical composition"
    ]
  },
  {
    "j": "歌",
    "e": [
      "song"
    ]
  },
  {
    "j": "謡",
    "e": [
      "song, noh chant"
    ]
  },
  {
    "j": "唄",
    "e": [
      "song"
    ]
  },
  {
    "j": "諧",
    "e": [
      "harmony"
    ]
  },
  {
    "j": "琴",
    "e": [
      "cithare, harp"
    ]
  },
  {
    "j": "笛",
    "e": [
      "flute"
    ]
  },
  {
    "j": "鼓",
    "e": [
      "drum"
    ]
  },
  {
    "j": "拍",
    "e": [
      "clap, beat (music)"
    ]
  },
  {
    "j": "節",
    "e": [
      "tune, melody"
    ]
  },
  {
    "j": "詩",
    "e": [
      "poetry"
    ]
  },
  {
    "j": "詠",
    "e": [
      "recite poetry"
    ]
  },
  {
    "j": "俳",
    "e": [
      "haiku"
    ]
  },
  {
    "j": "劇",
    "e": [
      "drama, play"
    ]
  },
  {
    "j": "祭",
    "e": [
      "festival"
    ]
  },
  {
    "j": "校",
    "e": [
      "school"
    ]
  },
  {
    "j": "学",
    "e": [
      "study, school"
    ]
  },
  {
    "j": "生",
    "e": [
      "student"
    ]
  },
  {
    "j": "塾",
    "e": [
      "private school"
    ]
  },
  {
    "j": "科",
    "e": [
      "faculty"
    ]
  },
  {
    "j": "教",
    "e": [
      "teach"
    ]
  },
  {
    "j": "究",
    "e": [
      "study, research"
    ]
  },
  {
    "j": "研",
    "e": [
      "study, research"
    ]
  },
  {
    "j": "知",
    "e": [
      "know"
    ]
  },
  {
    "j": "卒",
    "e": [
      "graduate"
    ]
  },
  {
    "j": "儒",
    "e": [
      "Confucianism"
    ]
  },
  {
    "j": "語",
    "e": [
      "language"
    ]
  },
  {
    "j": "言",
    "e": [
      "say"
    ]
  },
  {
    "j": "話",
    "e": [
      "speak"
    ]
  },
  {
    "j": "声",
    "e": [
      "voice"
    ]
  },
  {
    "j": "告",
    "e": [
      "tell"
    ]
  },
  {
    "j": "談",
    "e": [
      "discuss"
    ]
  },
  {
    "j": "聞",
    "e": [
      "ask"
    ]
  },
  {
    "j": "問",
    "e": [
      "question"
    ]
  },
  {
    "j": "答",
    "e": [
      "answer"
    ]
  },
  {
    "j": "吟",
    "e": [
      "recite"
    ]
  },
  {
    "j": "読",
    "e": [
      "read"
    ]
  },
  {
    "j": "書",
    "e": [
      "write"
    ]
  },
  {
    "j": "本",
    "e": [
      "book"
    ]
  },
  {
    "j": "文",
    "e": [
      "text"
    ]
  },
  {
    "j": "図",
    "e": [
      "map, diagram"
    ]
  },
  {
    "j": "筆",
    "e": [
      "writing, brush"
    ]
  },
  {
    "j": "字",
    "e": [
      "character"
    ]
  },
  {
    "j": "辞",
    "e": [
      "word"
    ]
  },
  {
    "j": "詞",
    "e": [
      "words"
    ]
  },
  {
    "j": "句",
    "e": [
      "phrase"
    ]
  },
  {
    "j": "記",
    "e": [
      "written record"
    ]
  },
  {
    "j": "刊",
    "e": [
      "publish"
    ]
  },
  {
    "j": "誌",
    "e": [
      "document, journal"
    ]
  },
  {
    "j": "訃",
    "e": [
      "obituary"
    ]
  },
  {
    "j": "信",
    "e": [
      "message"
    ]
  },
  {
    "j": "報",
    "e": [
      "inform"
    ]
  },
  {
    "j": "説",
    "e": [
      "explain"
    ]
  },
  {
    "j": "題",
    "e": [
      "topic"
    ]
  },
  {
    "j": "表",
    "e": [
      "express"
    ]
  },
  {
    "j": "伝",
    "e": [
      "transmit"
    ]
  },
  {
    "j": "論",
    "e": [
      "discourse"
    ]
  },
  {
    "j": "講",
    "e": [
      "lecture"
    ]
  },
  {
    "j": "宣",
    "e": [
      "proclaim"
    ]
  },
  {
    "j": "神",
    "e": [
      "god"
    ]
  },
  {
    "j": "宗",
    "e": [
      "religion, sect"
    ]
  },
  {
    "j": "教",
    "e": [
      "religion"
    ]
  },
  {
    "j": "聖",
    "e": [
      "sacred"
    ]
  },
  {
    "j": "祈",
    "e": [
      "pray"
    ]
  },
  {
    "j": "仏",
    "e": [
      "Buddha"
    ]
  },
  {
    "j": "寺",
    "e": [
      "Buddhist temple"
    ]
  },
  {
    "j": "僧",
    "e": [
      "Buddhist priest"
    ]
  },
  {
    "j": "尼",
    "e": [
      "Buddhist nun"
    ]
  },
  {
    "j": "禅",
    "e": [
      "Zen"
    ]
  },
  {
    "j": "社",
    "e": [
      "Shinto shrine"
    ]
  },
  {
    "j": "刹",
    "e": [
      "temple"
    ]
  },
  {
    "j": "詣",
    "e": [
      "temple visit"
    ]
  },
  {
    "j": "宮",
    "e": [
      "shrine"
    ]
  },
  {
    "j": "派",
    "e": [
      "sect"
    ]
  },
  {
    "j": "魂",
    "e": [
      "soul"
    ]
  },
  {
    "j": "霊",
    "e": [
      "spirit"
    ]
  },
  {
    "j": "魔",
    "e": [
      "demon, witch"
    ]
  },
  {
    "j": "鬼",
    "e": [
      "ghost, devil"
    ]
  },
  {
    "j": "幻",
    "e": [
      "phantom, apparition"
    ]
  },
  {
    "j": "竜",
    "e": [
      "dragon"
    ]
  },
  {
    "j": "武",
    "e": [
      "military"
    ]
  },
  {
    "j": "戦",
    "e": [
      "battle"
    ]
  },
  {
    "j": "闘",
    "e": [
      "battle"
    ]
  },
  {
    "j": "敵",
    "e": [
      "enemy"
    ]
  },
  {
    "j": "攻",
    "e": [
      "attack"
    ]
  },
  {
    "j": "斬",
    "e": [
      "slash"
    ]
  },
  {
    "j": "伐",
    "e": [
      "attack or punish"
    ]
  },
  {
    "j": "殺",
    "e": [
      "kill"
    ]
  },
  {
    "j": "撃",
    "e": [
      "attack"
    ]
  },
  {
    "j": "討",
    "e": [
      "attack"
    ]
  },
  {
    "j": "殴",
    "e": [
      "beat, assault"
    ]
  },
  {
    "j": "撃",
    "e": [
      "beat, attack"
    ]
  },
  {
    "j": "射",
    "e": [
      "shoot at"
    ]
  },
  {
    "j": "襲",
    "e": [
      "raid"
    ]
  },
  {
    "j": "征",
    "e": [
      "conquer"
    ]
  },
  {
    "j": "兵",
    "e": [
      "soldier"
    ]
  },
  {
    "j": "刀",
    "e": [
      "sword or katana"
    ]
  },
  {
    "j": "矛",
    "e": [
      "halberd"
    ]
  },
  {
    "j": "戈",
    "e": [
      "spear"
    ]
  },
  {
    "j": "剣",
    "e": [
      "sword"
    ]
  },
  {
    "j": "斬",
    "e": [
      "cut with a sword"
    ]
  },
  {
    "j": "盾",
    "e": [
      "shield"
    ]
  },
  {
    "j": "甲",
    "e": [
      "armour"
    ]
  },
  {
    "j": "侍",
    "e": [
      "samurai"
    ]
  },
  {
    "j": "忍",
    "e": [
      "ninja or shinobi"
    ]
  },
  {
    "j": "偵",
    "e": [
      "spy"
    ]
  },
  {
    "j": "弓",
    "e": [
      "bow"
    ]
  },
  {
    "j": "矢",
    "e": [
      "arrow"
    ]
  },
  {
    "j": "銃",
    "e": [
      "gun"
    ]
  },
  {
    "j": "砲",
    "e": [
      "gun or cannon"
    ]
  },
  {
    "j": "将",
    "e": [
      "commander"
    ]
  },
  {
    "j": "曹",
    "e": [
      "sergeant"
    ]
  },
  {
    "j": "尉",
    "e": [
      "military officer"
    ]
  },
  {
    "j": "軍",
    "e": [
      "troops"
    ]
  },
  {
    "j": "隊",
    "e": [
      "corps"
    ]
  },
  {
    "j": "班",
    "e": [
      "squad, corps"
    ]
  },
  {
    "j": "陣",
    "e": [
      "battle formation, camp"
    ]
  },
  {
    "j": "屯",
    "e": [
      "barracks"
    ]
  },
  {
    "j": "爆",
    "e": [
      "bomb"
    ]
  },
  {
    "j": "弾",
    "e": [
      "bullet"
    ]
  },
  {
    "j": "艦",
    "e": [
      "warship"
    ]
  }
]